text_preprocessing/__init__.py
text_preprocessing/text_preprocessing.py
text_preprocessing/data/custom_substitutions.csv
text_preprocessing/data/ignore_spellcheck_words.txt
text_preprocessing-0.1.1.dist-info/LICENSE
text_preprocessing-0.1.1.dist-info/METADATA
text_preprocessing-0.1.1.dist-info/WHEEL
text_preprocessing-0.1.1.dist-info/top_level.txt
text_preprocessing-0.1.1.dist-info/RECORD
