Metadata-Version: 2.1
Name: text-preprocessing
Version: 0.1.1
Summary: A python package for text preprocessing task in natural language processing
Home-page: https://github.com/berknology/text-preprocessing
Author: He Hao
Author-email: berknology@gmail.com
License: BSD license
Keywords: NLP
Classifier: Development Status :: 2 - Pre-Alpha
Classifier: Intended Audience :: Developers
Classifier: License :: OSI Approved :: BSD License
Classifier: Natural Language :: English
Classifier: Programming Language :: Python :: 3.7
Classifier: Programming Language :: Python :: 3.8
License-File: LICENSE
Requires-Dist: nltk
Requires-Dist: pyspellchecker
Requires-Dist: contractions
Requires-Dist: names-dataset (==2.1)
Requires-Dist: unittest-xml-reporting
